kekeutils/__init__.py
kekeutils/myfunctions.py
kekeutils-0.1.1.dist-info/METADATA
kekeutils-0.1.1.dist-info/WHEEL
kekeutils-0.1.1.dist-info/top_level.txt
kekeutils-0.1.1.dist-info/RECORD
