Metadata-Version: 2.1
Name: kekeutils
Version: 0.1.1
Summary: Kekeutils - The Ultimate Python Library
Home-page: UNKNOWN
Author: Jiro Leminen & Miika Lehtonen
License: MIT
Platform: UNKNOWN
